[
    {
        "Fipe": 43270.0,
        "UniqueId": 35925939
    },
    {
        "Fipe": 71931.0,
        "UniqueId": 35926195
    },
    {
        "Fipe": 73593.0,
        "UniqueId": 35925488
    },
    {
        "Fipe": 51487.0,
        "UniqueId": 35924588
    },
    {
        "Fipe": 24097.0,
        "UniqueId": 35929738
    },
    {
        "Fipe": 22300.0,
        "UniqueId": 35932598
    },
    {
        "Fipe": 34807.0,
        "UniqueId": 35932254
    },
    {
        "Fipe": 140963.0,
        "UniqueId": 35243486
    },
    {
        "Fipe": 86488.0,
        "UniqueId": 35934544
    },
    {
        "Fipe": 39424.0,
        "UniqueId": 22831692
    },
    {
        "Fipe": 175871.0,
        "UniqueId": 35092506
    },
    {
        "Fipe": 76730.0,
        "UniqueId": 33034633
    },
    {
        "Fipe": 9718.0,
        "UniqueId": 35936585
    },
    {
        "Fipe": 18724.0,
        "UniqueId": 35938878
    },
    {
        "Fipe": 84840.0,
        "UniqueId": 35933602
    },
    {
        "Fipe": 490591.0,
        "UniqueId": 22874861
    },
    {
        "Fipe": 95894.0,
        "UniqueId": 26780387
    },
    {
        "Fipe": 29879.0,
        "UniqueId": 12811465
    },
    {
        "Fipe": 118552.0,
        "UniqueId": 18996954
    },
    {
        "Fipe": 46982.0,
        "UniqueId": 14310254
    },
    {
        "Fipe": 86766.0,
        "UniqueId": 35700876
    },
    {
        "Fipe": 18587.0,
        "UniqueId": 34295584
    },
    {
        "Fipe": 27116.0,
        "UniqueId": 35832788
    },
    {
        "Fipe": 82315.0,
        "UniqueId": 35896215
    },
    {
        "Fipe": 340215.0,
        "UniqueId": 17308206
    },
    {
        "Fipe": 31140.0,
        "UniqueId": 33647105
    },
    {
        "Fipe": 80102.0,
        "UniqueId": 35898161
    },
    {
        "Fipe": 33645.0,
        "UniqueId": 35449563
    },
    {
        "Fipe": 126981.0,
        "UniqueId": 34934769
    },
    {
        "Fipe": 112759.0,
        "UniqueId": 32150676
    },
    {
        "Fipe": 162823.0,
        "UniqueId": 35097391
    },
    {
        "Fipe": 145138.0,
        "UniqueId": 35907731
    },
    {
        "Fipe": 82397.0,
        "UniqueId": 33803268
    },
    {
        "Fipe": 100406.0,
        "UniqueId": 30910911
    },
    {
        "Fipe": 408190.0,
        "UniqueId": 35874218
    },
    {
        "Fipe": 45433.0,
        "UniqueId": 29481788
    },
    {
        "Fipe": 48251.0,
        "UniqueId": 35448876
    },
    {
        "Fipe": 182825.0,
        "UniqueId": 33877113
    },
    {
        "Fipe": 92453.0,
        "UniqueId": 35005222
    },
    {
        "Fipe": 98078.0,
        "UniqueId": 27149671
    },
    {
        "Fipe": 278434.0,
        "UniqueId": 34693972
    },
    {
        "Fipe": 75816.0,
        "UniqueId": 29268064
    },
    {
        "Fipe": 25999.0,
        "UniqueId": 35120452
    },
    {
        "Fipe": 28840.0,
        "UniqueId": 35860025
    },
    {
        "Fipe": 135879.0,
        "UniqueId": 35679688
    },
    {
        "Fipe": 176892.0,
        "UniqueId": 29687267
    },
    {
        "Fipe": 73785.0,
        "UniqueId": 34604115
    },
    {
        "Fipe": 75816.0,
        "UniqueId": 27228315
    },
    {
        "Fipe": 99242.0,
        "UniqueId": 32965250
    },
    {
        "Fipe": 150637.0,
        "UniqueId": 27895329
    },
    {
        "Fipe": 148675.0,
        "UniqueId": 34477137
    },
    {
        "Fipe": 126460.0,
        "UniqueId": 35341874
    },
    {
        "Fipe": 75689.0,
        "UniqueId": 32859832
    },
    {
        "Fipe": 111076.0,
        "UniqueId": 35740285
    },
    {
        "Fipe": 104989.0,
        "UniqueId": 24434459
    },
    {
        "Fipe": 19412.0,
        "UniqueId": 35941384
    },
    {
        "Fipe": 199738.0,
        "UniqueId": 21309213
    },
    {
        "Fipe": 25999.0,
        "UniqueId": 35834432
    },
    {
        "Fipe": 209117.0,
        "UniqueId": 35744979
    },
    {
        "Fipe": 86766.0,
        "UniqueId": 35467879
    },
    {
        "Fipe": 35631.0,
        "UniqueId": 31234954
    },
    {
        "Fipe": 58003.0,
        "UniqueId": 32513574
    },
    {
        "Fipe": 31485.0,
        "UniqueId": 31657309
    },
    {
        "Fipe": 350215.0,
        "UniqueId": 35392333
    },
    {
        "Fipe": 20775.0,
        "UniqueId": 29546998
    },
    {
        "Fipe": 33754.0,
        "UniqueId": 31075409
    },
    {
        "Fipe": 44525.0,
        "UniqueId": 35941899
    },
    {
        "Fipe": 271317.0,
        "UniqueId": 35735352
    },
    {
        "Fipe": 56162.0,
        "UniqueId": 34750299
    },
    {
        "Fipe": 21444.0,
        "UniqueId": 34143368
    },
    {
        "Fipe": 32886.0,
        "UniqueId": 33733145
    },
    {
        "Fipe": 84727.0,
        "UniqueId": 35612162
    },
    {
        "Fipe": 66571.0,
        "UniqueId": 35186736
    },
    {
        "Fipe": 75689.0,
        "UniqueId": 35825327
    },
    {
        "Fipe": 104989.0,
        "UniqueId": 33044767
    },
    {
        "Fipe": 47854.0,
        "UniqueId": 35643338
    },
    {
        "Fipe": 72078.0,
        "UniqueId": 35668403
    },
    {
        "Fipe": 34230.0,
        "UniqueId": 25887501
    },
    {
        "Fipe": 176892.0,
        "UniqueId": 35692603
    },
    {
        "Fipe": 74893.0,
        "UniqueId": 35641649
    },
    {
        "Fipe": 33120.0,
        "UniqueId": 34723448
    },
    {
        "Fipe": 143086.0,
        "UniqueId": 35721521
    },
    {
        "Fipe": 115384.0,
        "UniqueId": 35893719
    },
    {
        "Fipe": 83821.0,
        "UniqueId": 32488858
    },
    {
        "Fipe": 36881.0,
        "UniqueId": 34990288
    },
    {
        "Fipe": 442426.0,
        "UniqueId": 34674487
    },
    {
        "Fipe": 0,
        "UniqueId": 35756648
    },
    {
        "Fipe": 24307.0,
        "UniqueId": 35441678
    },
    {
        "Fipe": 84778.0,
        "UniqueId": 35680422
    },
    {
        "Fipe": 63522.0,
        "UniqueId": 31880405
    },
    {
        "Fipe": 164064.0,
        "UniqueId": 35855239
    },
    {
        "Fipe": 16121.0,
        "UniqueId": 5284217
    },
    {
        "Fipe": 21118.0,
        "UniqueId": 35903423
    },
    {
        "Fipe": 542443.0,
        "UniqueId": 35726544
    },
    {
        "Fipe": 123134.0,
        "UniqueId": 32057561
    },
    {
        "Fipe": 339352.0,
        "UniqueId": 35693125
    }
]